setup.py
selenium_wrapper/__init__.py
selenium_wrapper/drivers.py
selenium_wrapper/screenshots.py
selenium_wrapper/selenium_wrapper_class.py
selenium_wrapper/tools.py
selenium_wrapper.egg-info/PKG-INFO
selenium_wrapper.egg-info/SOURCES.txt
selenium_wrapper.egg-info/dependency_links.txt
selenium_wrapper.egg-info/entry_points.txt
selenium_wrapper.egg-info/requires.txt
selenium_wrapper.egg-info/top_level.txt
selenium_wrapper/nose/__init__.py
selenium_wrapper/nose/webui_screenshots.py